<?xml version="1.0" encoding="utf-8"?>
<openerp>
    <data>
        <record id="act_nfse_ready" model="workflow.activity">
            <field name="wkf_id" ref="account.wkf"/>
            <field name="name">nfse_ready</field>
            <field name="action">write({'state':'nfse_ready'})</field>
            <field name="kind">function</field>
        </record>
        
        <record id="act_nfse_transmit" model="workflow.activity">
            <field name="wkf_id" ref="account.wkf"/>
            <field name="name">nfse_transmit</field>
            <field name="action">            
            	action_invoice_send_nfse()
            </field>
            <field name="kind">function</field>
        </record>               
		
        <record id="act_nfse_exception" model="workflow.activity">
            <field name="wkf_id" ref="account.wkf"/>
            <field name="name">nfse_exception</field>
            <field name="action">write({'state':'nfse_exception'})</field>
            <field name="kind">function</field>
        </record>        
       
        <record id="tras_router_open" model="workflow.transition">
            <field name="act_from" ref="l10n_br_account_product.act_router"/>
            <field name="act_to" ref="act_nfse_ready"/>
            <field name="condition">fiscal_type == 'service' and issuer == '0'</field>
        </record>
        
        <record id="account.t4" model="workflow.transition">
            <field name="act_from" ref="l10n_br_account_product.act_router"/>
            <field name="act_to" ref="account.act_open"/>
            <field name="condition">(fiscal_document_electronic == False and fiscal_type != 'service') or issuer == '1'</field>
            <field name="signal" eval="False" />
        </record>
        
        <record id="tras_nfse_ready_transmit" model="workflow.transition">
            <field name="act_from" ref="act_nfse_ready"/>
            <field name="act_to" ref="act_nfse_transmit"/>
            <field name="condition">True</field>
            <field name="signal">nfse_trysend</field>
        </record>        

        <record id="tras_nfse_ready_cancel" model="workflow.transition">
            <field name="act_from" ref="act_nfse_ready"/>
            <field name="act_to" ref="account.act_cancel"/>
            <field name="condition">True</field>
            <field name="signal">invoice_cancel</field>
        </record>

        <record id="tras_nfse_transmit_open" model="workflow.transition">
            <field name="act_from" ref="act_nfse_transmit"/>
            <field name="act_to" ref="account.act_open"/>
            <field name="condition">(state=='open')</field>
            <field name="signal">invoice_open</field>
        </record>

        <record id="tras_nfse_transmit_exception" model="workflow.transition">
            <field name="act_from" ref="act_nfse_transmit"/>
            <field name="act_to" ref="act_nfse_exception"/>
            <field name="condition">(state=='nfse_exception')</field>
            <field name="signal" eval="False"/>
        </record>


        <record id="tras_nfse_exception_cancel" model="workflow.transition">
            <field name="act_from" ref="act_nfse_exception"/>
            <field name="act_to" ref="account.act_cancel"/>
            <field name="condition">True</field>
            <field name="signal">invoice_cancel</field>
        </record>
        
        <record id="tras_nfse_exception_cancel" model="workflow.transition">
            <field name="act_from" ref="act_nfse_exception"/>
            <field name="act_to" ref="act_nfse_ready" />
            <field name="condition">True</field>
            <field name="signal">nfse_resend</field>
        </record>        

    </data>
</openerp>